{
  "id": "power_beam", 
  "name": "Beam",
  "world_link": "POWER",
  "texts": [
    {  
	  "id": 0,
      "text": "Массивное бревно покоится под ясным небом",
      "answers": [
        {
          "text": "(Сарказм): Ну что, старина-бревно, как жизнь?",
          "emotion": "SADNESS",
          "sign": true
        },
        {
          "text": "(Раздраженно): И чего молчишь?",
          "emotion": "ANGER", 
          "sign": true
        },
        {
          "text": "(С опаской): Ты... ты ведь не превратишься сейчас в кого-нибудь?",
          "emotion": "FEAR",
          "sign": true
        }
      ]
    },
    {	
	  "id": 1,
      "text": "(Бревно молчит. Ветер шелестит листьями)",
      "answers": []
    }
  ]
}